
<persistence xmlns="http://java.sun.com/xml/ns/persistence"
             xmlns:xsi="http://www.w3.org/2001/XMLSchema-instance"
             xsi:schemaLocation="http://java.sun.com/xml/ns/persistence http://java.sun.com/xml/ns/persistence/persistence_2_0.xsd"
             version="2.0">
             
	<persistence-unit name="worldgen">
		<provider>org.hibernate.ejb.HibernatePersistence</provider>
		
		<class>uk.org.glendale.worldgen.astro.sector.Sector</class>
		<class>uk.org.glendale.worldgen.astro.starsystem.StarSystem</class>
		<class>uk.org.glendale.worldgen.astro.planet.Planet</class>
		<class>uk.org.glendale.worldgen.astro.star.Star</class>
		<class>uk.org.glendale.worldgen.civ.commodity.Commodity</class>
		<class>uk.org.glendale.worldgen.astro.planet.Resource</class>
				
		<properties>
			<property name="hibernate.archive.autodetection" value="class"/>
			
			<property name="hibernate.show_sql" value="false"/>
			<property name="hibernate.format_sql" value="true"/>		
		</properties>

	</persistence-unit>
</persistence>
